Workbook
Name ExpenseData: 'Daily Expenses'!$A$2:$I$201
Name ExpenseDates: 'Daily Expenses'!$A$2:$A$201
Name ExpenseAmounts: 'Daily Expenses'!$G$2:$G$201
Name ExpenseCategories: 'Daily Expenses'!$C$2:$C$201
Name MonthlyTotals: 'Monthly Summary'!$B$3:$B$14
Name CategoryTotals: 'Category Analysis'!$B$3:$B$17

Sheet Dashboard
A1: Smart Personal Expense Tracker XL | Dashboard
B2: MONTHLY SPENDING | H2: WEEKLY SPENDING | N2: DAILY AVERAGE
B4: =SUMPRODUCT((MONTH('Daily Expenses'!$A$2:$A$201)=MONTH(TODAY()))*(YEAR('Daily Expenses'!$A$2:$A$201)=YEAR(TODAY()))*'Daily Expenses'!$G$2:$G$201) | H4: =SUMPRODUCT(('Daily Expenses'!$A$2:$A$201>=TODAY()-WEEKDAY(TODAY(),2)+1)*('Daily Expenses'!$A$2:$A$201<=TODAY()-WEEKDAY(TODAY(),2)+7)*'Daily Expenses'!$G$2:$G$201) | N4: =IFERROR(SUMPRODUCT(('Daily Expenses'!$G$2:$G$201<>"")*'Daily Expenses'!$G$2:$G$201)/SUMPRODUCT(--('Daily Expenses'!$G$2:$G$201<>"")),0)
B7: REMAINING BUDGET | H7: TOP CATEGORY | N7: TOTAL EXPENSES
B9: =IFERROR('Budget Tracking'!B5-SUMPRODUCT((MONTH('Daily Expenses'!$A$2:$A$201)=MONTH(TODAY()))*(YEAR('Daily Expenses'!$A$2:$A$201)=YEAR(TODAY()))*'Daily Expenses'!$G$2:$G$201),0) | H9: =IFERROR(INDEX('Category Analysis'!$A$3:$A$17,MATCH(MAX('Category Analysis'!$B$3:$B$17),'Category Analysis'!$B$3:$B$17,0)),"N/A") | N9: =IFERROR(SUM('Daily Expenses'!$G$2:$G$201),0)
B12: Expense Analytics

Sheet Daily Expenses
A1: Date | B1: Product Name | C1: Category | D1: Store Name | E1: Quantity | F1: Price Per Unit | G1: Total Price | H1: Payment Method | I1: Notes
A2: 45294 | B2: Migros Weekly Shop | C2: Food | D2: Migros | E2: 1 | F2: 87.5 | G2: =IF(OR(E2="",F2=""),"",E2*F2) | H2: Card | I2: Weekly groceries
A3: 45296 | B3: SBB Monthly Pass | C3: Transport | D3: SBB | E3: 1 | F3: 86 | G3: =IF(OR(E3="",F3=""),"",E3*F3) | H3: Bank Transfer | I3: Public transport
A4: 45298 | B4: Chicken Breast 1kg | C4: Meat | D4: Coop | E4: 2 | F4: 12.9 | G4: =IF(OR(E4="",F4=""),"",E4*F4) | H4: Card | I4: Protein source
A5: 45300 | B5: Protein Powder | C5: Supplements | D5: Sportxx | E5: 1 | F5: 49.9 | G5: =IF(OR(E5="",F5=""),"",E5*F5) | H5: Card | I5: Whey protein
A6: 45301 | B6: Pharmacy Visit | C6: Health | D6: Apotheke | E6: 1 | F6: 23.4 | G6: =IF(OR(E6="",F6=""),"",E6*F6) | H6: Cash | I6: Cold medicine
A7: 45303 | B7: Netflix | C7: Entertainment | D7: Netflix | E7: 1 | F7: 17.9 | G7: =IF(OR(E7="",F7=""),"",E7*F7) | H7: Card | I7: Monthly sub
A8: 45305 | B8: Fresh Vegetables | C8: Vegetables | D8: Coop | E8: 1 | F8: 18.6 | G8: =IF(OR(E8="",F8=""),"",E8*F8) | H8: Card | I8: Weekly veg
A9: 45307 | B9: iPhone Cable | C9: Electronics | D9: Media Markt | E9: 1 | F9: 29 | G9: =IF(OR(E9="",F9=""),"",E9*F9) | H9: Card | I9: Replacement
A10: 45309 | B10: Gym Membership | C10: Health | D10: Fitness Park | E10: 1 | F10: 65 | G10: =IF(OR(E10="",F10=""),"",E10*F10) | H10: Bank Transfer | I10: Monthly fee
A11: 45311 | B11: Red Bull 4-pack | C11: Drinks | D11: Migros | E11: 2 | F11: 6.5 | G11: =IF(OR(E11="",F11=""),"",E11*F11) | H11: Cash | I11: Energy drinks
G12: =IF(OR(E12="",F12=""),"",E12*F12)
G13: =IF(OR(E13="",F13=""),"",E13*F13)
G14: =IF(OR(E14="",F14=""),"",E14*F14)
G15: =IF(OR(E15="",F15=""),"",E15*F15)
G16: =IF(OR(E16="",F16=""),"",E16*F16)
G17: =IF(OR(E17="",F17=""),"",E17*F17)
G18: =IF(OR(E18="",F18=""),"",E18*F18)
G19: =IF(OR(E19="",F19=""),"",E19*F19)
G20: =IF(OR(E20="",F20=""),"",E20*F20)
G21: =IF(OR(E21="",F21=""),"",E21*F21)
G22: =IF(OR(E22="",F22=""),"",E22*F22)
G23: =IF(OR(E23="",F23=""),"",E23*F23)
... G201: =IF(OR(E201="",F201=""),"",E201*F201)

Sheet Monthly Summary
A1: Monthly Expense Summary
A2: Month | B2: Total Spending | C2: Transactions | D2: Avg Daily | E2: Highest Expense | F2: Budget | G2: % Used | H2: Status
A3: Jan | B3: =SUMPRODUCT(('Daily Expenses'!$G$2:$G$201)*(MONTH('Daily Expenses'!$A$2:$A$201)=1)*(YEAR('Daily Expenses'!$A$2:$A$201)=YEAR(TODAY()))) | C3: =SUMPRODUCT((MONTH('Daily Expenses'!$A$2:$A$201)=1)*(YEAR('Daily Expenses'!$A$2:$A$201)=YEAR(TODAY()))*('Daily Expenses'!$G$2:$G$201<>"")) | D3: =IFERROR(B3/DAY(EOMONTH(DATE(YEAR(TODAY()),1,1),0)),0) | E3: =IFERROR(MAXIFS('Daily Expenses'!$G$2:$G$201,'Daily Expenses'!$A$2:$A$201,">="&DATE(YEAR(TODAY()),1,1),'Daily Expenses'!$A$2:$A$201,"<"&DATE(YEAR(TODAY()),1+1,1)),0) | F3: ='Budget Tracking'!B5 | G3: =IFERROR(B3/F3,0) | H3: =IF(G3>1,"Over Budget ▲",IF(G3>0.8,"Near Limit ⚠","On Track ✓"))
A4: Feb | B4: =SUMPRODUCT(('Daily Expenses'!$G$2:$G$201)*(MONTH('Daily Expenses'!$A$2:$A$201)=2)*(YEAR('Daily Expenses'!$A$2:$A$201)=YEAR(TODAY()))) | C4: =SUMPRODUCT((MONTH('Daily Expenses'!$A$2:$A$201)=2)*(YEAR('Daily Expenses'!$A$2:$A$201)=YEAR(TODAY()))*('Daily Expenses'!$G$2:$G$201<>"")) | D4: =IFERROR(B4/DAY(EOMONTH(DATE(YEAR(TODAY()),2,1),0)),0) | E4: =IFERROR(MAXIFS('Daily Expenses'!$G$2:$G$201,'Daily Expenses'!$A$2:$A$201,">="&DATE(YEAR(TODAY()),2,1),'Daily Expenses'!$A$2:$A$201,"<"&DATE(YEAR(TODAY()),2+1,1)),0) | F4: ='Budget Tracking'!B5 | G4: =IFERROR(B4/F4,0) | H4: =IF(G4>1,"Over Budget ▲",IF(G4>0.8,"Near Limit ⚠","On Track ✓"))
A5: Mar | B5: =SUMPRODUCT(('Daily Expenses'!$G$2:$G$201)*(MONTH('Daily Expenses'!$A$2:$A$201)=3)*(YEAR('Daily Expenses'!$A$2:$A$201)=YEAR(TODAY()))) | C5: =SUMPRODUCT((MONTH('Daily Expenses'!$A$2:$A$201)=3)*(YEAR('Daily Expenses'!$A$2:$A$201)=YEAR(TODAY()))*('Daily Expenses'!$G$2:$G$201<>"")) | D5: =IFERROR(B5/DAY(EOMONTH(DATE(YEAR(TODAY()),3,1),0)),0) | E5: =IFERROR(MAXIFS('Daily Expenses'!$G$2:$G$201,'Daily Expenses'!$A$2:$A$201,">="&DATE(YEAR(TODAY()),3,1),'Daily Expenses'!$A$2:$A$201,"<"&DATE(YEAR(TODAY()),3+1,1)),0) | F5: ='Budget Tracking'!B5 | G5: =IFERROR(B5/F5,0) | H5: =IF(G5>1,"Over Budget ▲",IF(G5>0.8,"Near Limit ⚠","On Track ✓"))
A6: Apr | B6: =SUMPRODUCT(('Daily Expenses'!$G$2:$G$201)*(MONTH('Daily Expenses'!$A$2:$A$201)=4)*(YEAR('Daily Expenses'!$A$2:$A$201)=YEAR(TODAY()))) | C6: =SUMPRODUCT((MONTH('Daily Expenses'!$A$2:$A$201)=4)*(YEAR('Daily Expenses'!$A$2:$A$201)=YEAR(TODAY()))*('Daily Expenses'!$G$2:$G$201<>"")) | D6: =IFERROR(B6/DAY(EOMONTH(DATE(YEAR(TODAY()),4,1),0)),0) | E6: =IFERROR(MAXIFS('Daily Expenses'!$G$2:$G$201,'Daily Expenses'!$A$2:$A$201,">="&DATE(YEAR(TODAY()),4,1),'Daily Expenses'!$A$2:$A$201,"<"&DATE(YEAR(TODAY()),4+1,1)),0) | F6: ='Budget Tracking'!B5 | G6: =IFERROR(B6/F6,0) | H6: =IF(G6>1,"Over Budget ▲",IF(G6>0.8,"Near Limit ⚠","On Track ✓"))
A7: May | B7: =SUMPRODUCT(('Daily Expenses'!$G$2:$G$201)*(MONTH('Daily Expenses'!$A$2:$A$201)=5)*(YEAR('Daily Expenses'!$A$2:$A$201)=YEAR(TODAY()))) | C7: =SUMPRODUCT((MONTH('Daily Expenses'!$A$2:$A$201)=5)*(YEAR('Daily Expenses'!$A$2:$A$201)=YEAR(TODAY()))*('Daily Expenses'!$G$2:$G$201<>"")) | D7: =IFERROR(B7/DAY(EOMONTH(DATE(YEAR(TODAY()),5,1),0)),0) | E7: =IFERROR(MAXIFS('Daily Expenses'!$G$2:$G$201,'Daily Expenses'!$A$2:$A$201,">="&DATE(YEAR(TODAY()),5,1),'Daily Expenses'!$A$2:$A$201,"<"&DATE(YEAR(TODAY()),5+1,1)),0) | F7: ='Budget Tracking'!B5 | G7: =IFERROR(B7/F7,0) | H7: =IF(G7>1,"Over Budget ▲",IF(G7>0.8,"Near Limit ⚠","On Track ✓"))
A8: Jun | B8: =SUMPRODUCT(('Daily Expenses'!$G$2:$G$201)*(MONTH('Daily Expenses'!$A$2:$A$201)=6)*(YEAR('Daily Expenses'!$A$2:$A$201)=YEAR(TODAY()))) | C8: =SUMPRODUCT((MONTH('Daily Expenses'!$A$2:$A$201)=6)*(YEAR('Daily Expenses'!$A$2:$A$201)=YEAR(TODAY()))*('Daily Expenses'!$G$2:$G$201<>"")) | D8: =IFERROR(B8/DAY(EOMONTH(DATE(YEAR(TODAY()),6,1),0)),0) | E8: =IFERROR(MAXIFS('Daily Expenses'!$G$2:$G$201,'Daily Expenses'!$A$2:$A$201,">="&DATE(YEAR(TODAY()),6,1),'Daily Expenses'!$A$2:$A$201,"<"&DATE(YEAR(TODAY()),6+1,1)),0) | F8: ='Budget Tracking'!B5 | G8: =IFERROR(B8/F8,0) | H8: =IF(G8>1,"Over Budget ▲",IF(G8>0.8,"Near Limit ⚠","On Track ✓"))
A9: Jul | B9: =SUMPRODUCT(('Daily Expenses'!$G$2:$G$201)*(MONTH('Daily Expenses'!$A$2:$A$201)=7)*(YEAR('Daily Expenses'!$A$2:$A$201)=YEAR(TODAY()))) | C9: =SUMPRODUCT((MONTH('Daily Expenses'!$A$2:$A$201)=7)*(YEAR('Daily Expenses'!$A$2:$A$201)=YEAR(TODAY()))*('Daily Expenses'!$G$2:$G$201<>"")) | D9: =IFERROR(B9/DAY(EOMONTH(DATE(YEAR(TODAY()),7,1),0)),0) | E9: =IFERROR(MAXIFS('Daily Expenses'!$G$2:$G$201,'Daily Expenses'!$A$2:$A$201,">="&DATE(YEAR(TODAY()),7,1),'Daily Expenses'!$A$2:$A$201,"<"&DATE(YEAR(TODAY()),7+1,1)),0) | F9: ='Budget Tracking'!B5 | G9: =IFERROR(B9/F9,0) | H9: =IF(G9>1,"Over Budget ▲",IF(G9>0.8,"Near Limit ⚠","On Track ✓"))
A10: Aug | B10: =SUMPRODUCT(('Daily Expenses'!$G$2:$G$201)*(MONTH('Daily Expenses'!$A$2:$A$201)=8)*(YEAR('Daily Expenses'!$A$2:$A$201)=YEAR(TODAY()))) | C10: =SUMPRODUCT((MONTH('Daily Expenses'!$A$2:$A$201)=8)*(YEAR('Daily Expenses'!$A$2:$A$201)=YEAR(TODAY()))*('Daily Expenses'!$G$2:$G$201<>"")) | D10: =IFERROR(B10/DAY(EOMONTH(DATE(YEAR(TODAY()),8,1),0)),0) | E10: =IFERROR(MAXIFS('Daily Expenses'!$G$2:$G$201,'Daily Expenses'!$A$2:$A$201,">="&DATE(YEAR(TODAY()),8,1),'Daily Expenses'!$A$2:$A$201,"<"&DATE(YEAR(TODAY()),8+1,1)),0) | F10: ='Budget Tracking'!B5 | G10: =IFERROR(B10/F10,0) | H10: =IF(G10>1,"Over Budget ▲",IF(G10>0.8,"Near Limit ⚠","On Track ✓"))
A11: Sep | B11: =SUMPRODUCT(('Daily Expenses'!$G$2:$G$201)*(MONTH('Daily Expenses'!$A$2:$A$201)=9)*(YEAR('Daily Expenses'!$A$2:$A$201)=YEAR(TODAY()))) | C11: =SUMPRODUCT((MONTH('Daily Expenses'!$A$2:$A$201)=9)*(YEAR('Daily Expenses'!$A$2:$A$201)=YEAR(TODAY()))*('Daily Expenses'!$G$2:$G$201<>"")) | D11: =IFERROR(B11/DAY(EOMONTH(DATE(YEAR(TODAY()),9,1),0)),0) | E11: =IFERROR(MAXIFS('Daily Expenses'!$G$2:$G$201,'Daily Expenses'!$A$2:$A$201,">="&DATE(YEAR(TODAY()),9,1),'Daily Expenses'!$A$2:$A$201,"<"&DATE(YEAR(TODAY()),9+1,1)),0) | F11: ='Budget Tracking'!B5 | G11: =IFERROR(B11/F11,0) | H11: =IF(G11>1,"Over Budget ▲",IF(G11>0.8,"Near Limit ⚠","On Track ✓"))
A12: Oct | B12: =SUMPRODUCT(('Daily Expenses'!$G$2:$G$201)*(MONTH('Daily Expenses'!$A$2:$A$201)=10)*(YEAR('Daily Expenses'!$A$2:$A$201)=YEAR(TODAY()))) | C12: =SUMPRODUCT((MONTH('Daily Expenses'!$A$2:$A$201)=10)*(YEAR('Daily Expenses'!$A$2:$A$201)=YEAR(TODAY()))*('Daily Expenses'!$G$2:$G$201<>"")) | D12: =IFERROR(B12/DAY(EOMONTH(DATE(YEAR(TODAY()),10,1),0)),0) | E12: =IFERROR(MAXIFS('Daily Expenses'!$G$2:$G$201,'Daily Expenses'!$A$2:$A$201,">="&DATE(YEAR(TODAY()),10,1),'Daily Expenses'!$A$2:$A$201,"<"&DATE(YEAR(TODAY()),10+1,1)),0) | F12: ='Budget Tracking'!B5 | G12: =IFERROR(B12/F12,0) | H12: =IF(G12>1,"Over Budget ▲",IF(G12>0.8,"Near Limit ⚠","On Track ✓"))
A13: Nov | B13: =SUMPRODUCT(('Daily Expenses'!$G$2:$G$201)*(MONTH('Daily Expenses'!$A$2:$A$201)=11)*(YEAR('Daily Expenses'!$A$2:$A$201)=YEAR(TODAY()))) | C13: =SUMPRODUCT((MONTH('Daily Expenses'!$A$2:$A$201)=11)*(YEAR('Daily Expenses'!$A$2:$A$201)=YEAR(TODAY()))*('Daily Expenses'!$G$2:$G$201<>"")) | D13: =IFERROR(B13/DAY(EOMONTH(DATE(YEAR(TODAY()),11,1),0)),0) | E13: =IFERROR(MAXIFS('Daily Expenses'!$G$2:$G$201,'Daily Expenses'!$A$2:$A$201,">="&DATE(YEAR(TODAY()),11,1),'Daily Expenses'!$A$2:$A$201,"<"&DATE(YEAR(TODAY()),11+1,1)),0) | F13: ='Budget Tracking'!B5 | G13: =IFERROR(B13/F13,0) | H13: =IF(G13>1,"Over Budget ▲",IF(G13>0.8,"Near Limit ⚠","On Track ✓"))
A14: Dec | B14: =SUMPRODUCT(('Daily Expenses'!$G$2:$G$201)*(MONTH('Daily Expenses'!$A$2:$A$201)=12)*(YEAR('Daily Expenses'!$A$2:$A$201)=YEAR(TODAY()))) | C14: =SUMPRODUCT((MONTH('Daily Expenses'!$A$2:$A$201)=12)*(YEAR('Daily Expenses'!$A$2:$A$201)=YEAR(TODAY()))*('Daily Expenses'!$G$2:$G$201<>"")) | D14: =IFERROR(B14/DAY(EOMONTH(DATE(YEAR(TODAY()),12,1),0)),0) | E14: =IFERROR(MAXIFS('Daily Expenses'!$G$2:$G$201,'Daily Expenses'!$A$2:$A$201,">="&DATE(YEAR(TODAY()),12,1),'Daily Expenses'!$A$2:$A$201,"<"&DATE(YEAR(TODAY()),12+1,1)),0) | F14: ='Budget Tracking'!B5 | G14: =IFERROR(B14/F14,0) | H14: =IF(G14>1,"Over Budget ▲",IF(G14>0.8,"Near Limit ⚠","On Track ✓"))
A15: TOTAL | B15: =SUM(B3:B14) | C15: =SUM(C3:C14) | D15: =IFERROR(B15/SUMPRODUCT((B3:B14>0)*DAY(EOMONTH(DATE(YEAR(TODAY()),ROW(INDIRECT("1:12")),1),0))),0) | E15: =MAX(E3:E14)
A17: Category Breakdown by Month
A18: Category | B18: Jan | C18: Feb | D18: Mar | E18: Apr | F18: May | G18: Jun | H18: Jul | I18: Aug | J18: Sep | K18: Oct | L18: Nov | M18: Dec
A19: Food | B19: =SUMPRODUCT(('Daily Expenses'!$G$2:$G$201)*(MONTH('Daily Expenses'!$A$2:$A$201)=1)*(YEAR('Daily Expenses'!$A$2:$A$201)=YEAR(TODAY()))*('Daily Expenses'!$C$2:$C$201="Food")) | C19: =SUMPRODUCT(('Daily Expenses'!$G$2:$G$201)*(MONTH('Daily Expenses'!$A$2:$A$201)=2)*(YEAR('Daily Expenses'!$A$2:$A$201)=YEAR(TODAY()))*('Daily Expenses'!$C$2:$C$201="Food")) | D19: =SUMPRODUCT(('Daily Expenses'!$G$2:$G$201)*(MONTH('Daily Expenses'!$A$2:$A$201)=3)*(YEAR('Daily Expenses'!$A$2:$A$201)=YEAR(TODAY()))*('Daily Expenses'!$C$2:$C$201="Food")) | E19: =SUMPRODUCT(('Daily Expenses'!$G$2:$G$201)*(MONTH('Daily Expenses'!$A$2:$A$201)=4)*(YEAR('Daily Expenses'!$A$2:$A$201)=YEAR(TODAY()))*('Daily Expenses'!$C$2:$C$201="Food")) | F19: =SUMPRODUCT(('Daily Expenses'!$G$2:$G$201)*(MONTH('Daily Expenses'!$A$2:$A$201)=5)*(YEAR('Daily Expenses'!$A$2:$A$201)=YEAR(TODAY()))*('Daily Expenses'!$C$2:$C$201="Food")) | G19: =SUMPRODUCT(('Daily Expenses'!$G$2:$G$201)*(MONTH('Daily Expenses'!$A$2:$A$201)=6)*(YEAR('Daily Expenses'!$A$2:$A$201)=YEAR(TODAY()))*('Daily Expenses'!$C$2:$C$201="Food")) | H19: =SUMPRODUCT(('Daily Expenses'!$G$2:$G$201)*(MONTH('Daily Expenses'!$A$2:$A$201)=7)*(YEAR('Daily Expenses'!$A$2:$A$201)=YEAR(TODAY()))*('Daily Expenses'!$C$2:$C$201="Food")) | I19: =SUMPRODUCT(('Daily Expenses'!$G$2:$G$201)*(MONTH('Daily Expenses'!$A$2:$A$201)=8)*(YEAR('Daily Expenses'!$A$2:$A$201)=YEAR(TODAY()))*('Daily Expenses'!$C$2:$C$201="Food")) | J19: =SUMPRODUCT(('Daily Expenses'!$G$2:$G$201)*(MONTH('Daily Expenses'!$A$2:$A$201)=9)*(YEAR('Daily Expenses'!$A$2:$A$201)=YEAR(TODAY()))*('Daily Expenses'!$C$2:$C$201="Food")) | K19: =SUMPRODUCT(('Daily Expenses'!$G$2:$G$201)*(MONTH('Daily Expenses'!$A$2:$A$201)=10)*(YEAR('Daily Expenses'!$A$2:$A$201)=YEAR(TODAY()))*('Daily Expenses'!$C$2:$C$201="Food")) | L19: =SUMPRODUCT(('Daily Expenses'!$G$2:$G$201)*(MONTH('Daily Expenses'!$A$2:$A$201)=11)*(YEAR('Daily Expenses'!$A$2:$A$201)=YEAR(TODAY()))*('Daily Expenses'!$C$2:$C$201="Food")) | M19: =SUMPRODUCT(('Daily Expenses'!$G$2:$G$201)*(MONTH('Daily Expenses'!$A$2:$A$201)=12)*(YEAR('Daily Expenses'!$A$2:$A$201)=YEAR(TODAY()))*('Daily Expenses'!$C$2:$C$201="Food"))
A20: Vegetables | B20: =SUMPRODUCT(('Daily Expenses'!$G$2:$G$201)*(MONTH('Daily Expenses'!$A$2:$A$201)=1)*(YEAR('Daily Expenses'!$A$2:$A$201)=YEAR(TODAY()))*('Daily Expenses'!$C$2:$C$201="Vegetables")) | C20: =SUMPRODUCT(('Daily Expenses'!$G$2:$G$201)*(MONTH('Daily Expenses'!$A$2:$A$201)=2)*(YEAR('Daily Expenses'!$A$2:$A$201)=YEAR(TODAY()))*('Daily Expenses'!$C$2:$C$201="Vegetables")) | D20: =SUMPRODUCT(('Daily Expenses'!$G$2:$G$201)*(MONTH('Daily Expenses'!$A$2:$A$201)=3)*(YEAR('Daily Expenses'!$A$2:$A$201)=YEAR(TODAY()))*('Daily Expenses'!$C$2:$C$201="Vegetables")) | E20: =SUMPRODUCT(('Daily Expenses'!$G$2:$G$201)*(MONTH('Daily Expenses'!$A$2:$A$201)=4)*(YEAR('Daily Expenses'!$A$2:$A$201)=YEAR(TODAY()))*('Daily Expenses'!$C$2:$C$201="Vegetables")) | F20: =SUMPRODUCT(('Daily Expenses'!$G$2:$G$201)*(MONTH('Daily Expenses'!$A$2:$A$201)=5)*(YEAR('Daily Expenses'!$A$2:$A$201)=YEAR(TODAY()))*('Daily Expenses'!$C$2:$C$201="Vegetables")) | G20: =SUMPRODUCT(('Daily Expenses'!$G$2:$G$201)*(MONTH('Daily Expenses'!$A$2:$A$201)=6)*(YEAR('Daily Expenses'!$A$2:$A$201)=YEAR(TODAY()))*('Daily Expenses'!$C$2:$C$201="Vegetables")) | H20: =SUMPRODUCT(('Daily Expenses'!$G$2:$G$201)*(MONTH('Daily Expenses'!$A$2:$A$201)=7)*(YEAR('Daily Expenses'!$A$2:$A$201)=YEAR(TODAY()))*('Daily Expenses'!$C$2:$C$201="Vegetables")) | I20: =SUMPRODUCT(('Daily Expenses'!$G$2:$G$201)*(MONTH('Daily Expenses'!$A$2:$A$201)=8)*(YEAR('Daily Expenses'!$A$2:$A$201)=YEAR(TODAY()))*('Daily Expenses'!$C$2:$C$201="Vegetables")) | J20: =SUMPRODUCT(('Daily Expenses'!$G$2:$G$201)*(MONTH('Daily Expenses'!$A$2:$A$201)=9)*(YEAR('Daily Expenses'!$A$2:$A$201)=YEAR(TODAY()))*('Daily Expenses'!$C$2:$C$201="Vegetables")) | K20: =SUMPRODUCT(('Daily Expenses'!$G$2:$G$201)*(MONTH('Daily Expenses'!$A$2:$A$201)=10)*(YEAR('Daily Expenses'!$A$2:$A$201)=YEAR(TODAY()))*('Daily Expenses'!$C$2:$C$201="Vegetables")) | L20: =SUMPRODUCT(('Daily Expenses'!$G$2:$G$201)*(MONTH('Daily Expenses'!$A$2:$A$201)=11)*(YEAR('Daily Expenses'!$A$2:$A$201)=YEAR(TODAY()))*('Daily Expenses'!$C$2:$C$201="Vegetables")) | M20: =SUMPRODUCT(('Daily Expenses'!$G$2:$G$201)*(MONTH('Daily Expenses'!$A$2:$A$201)=12)*(YEAR('Daily Expenses'!$A$2:$A$201)=YEAR(TODAY()))*('Daily Expenses'!$C$2:$C$201="Vegetables"))
A21: Meat | B21: =SUMPRODUCT(('Daily Expenses'!$G$2:$G$201)*(MONTH('Daily Expenses'!$A$2:$A$201)=1)*(YEAR('Daily Expenses'!$A$2:$A$201)=YEAR(TODAY()))*('Daily Expenses'!$C$2:$C$201="Meat")) | C21: =SUMPRODUCT(('Daily Expenses'!$G$2:$G$201)*(MONTH('Daily Expenses'!$A$2:$A$201)=2)*(YEAR('Daily Expenses'!$A$2:$A$201)=YEAR(TODAY()))*('Daily Expenses'!$C$2:$C$201="Meat")) | D21: =SUMPRODUCT(('Daily Expenses'!$G$2:$G$201)*(MONTH('Daily Expenses'!$A$2:$A$201)=3)*(YEAR('Daily Expenses'!$A$2:$A$201)=YEAR(TODAY()))*('Daily Expenses'!$C$2:$C$201="Meat")) | E21: =SUMPRODUCT(('Daily Expenses'!$G$2:$G$201)*(MONTH('Daily Expenses'!$A$2:$A$201)=4)*(YEAR('Daily Expenses'!$A$2:$A$201)=YEAR(TODAY()))*('Daily Expenses'!$C$2:$C$201="Meat")) | F21: =SUMPRODUCT(('Daily Expenses'!$G$2:$G$201)*(MONTH('Daily Expenses'!$A$2:$A$201)=5)*(YEAR('Daily Expenses'!$A$2:$A$201)=YEAR(TODAY()))*('Daily Expenses'!$C$2:$C$201="Meat")) | G21: =SUMPRODUCT(('Daily Expenses'!$G$2:$G$201)*(MONTH('Daily Expenses'!$A$2:$A$201)=6)*(YEAR('Daily Expenses'!$A$2:$A$201)=YEAR(TODAY()))*('Daily Expenses'!$C$2:$C$201="Meat")) | H21: =SUMPRODUCT(('Daily Expenses'!$G$2:$G$201)*(MONTH('Daily Expenses'!$A$2:$A$201)=7)*(YEAR('Daily Expenses'!$A$2:$A$201)=YEAR(TODAY()))*('Daily Expenses'!$C$2:$C$201="Meat")) | I21: =SUMPRODUCT(('Daily Expenses'!$G$2:$G$201)*(MONTH('Daily Expenses'!$A$2:$A$201)=8)*(YEAR('Daily Expenses'!$A$2:$A$201)=YEAR(TODAY()))*('Daily Expenses'!$C$2:$C$201="Meat")) | J21: =SUMPRODUCT(('Daily Expenses'!$G$2:$G$201)*(MONTH('Daily Expenses'!$A$2:$A$201)=9)*(YEAR('Daily Expenses'!$A$2:$A$201)=YEAR(TODAY()))*('Daily Expenses'!$C$2:$C$201="Meat")) | K21: =SUMPRODUCT(('Daily Expenses'!$G$2:$G$201)*(MONTH('Daily Expenses'!$A$2:$A$201)=10)*(YEAR('Daily Expenses'!$A$2:$A$201)=YEAR(TODAY()))*('Daily Expenses'!$C$2:$C$201="Meat")) | L21: =SUMPRODUCT(('Daily Expenses'!$G$2:$G$201)*(MONTH('Daily Expenses'!$A$2:$A$201)=11)*(YEAR('Daily Expenses'!$A$2:$A$201)=YEAR(TODAY()))*('Daily Expenses'!$C$2:$C$201="Meat")) | M21: =SUMPRODUCT(('Daily Expenses'!$G$2:$G$201)*(MONTH('Daily Expenses'!$A$2:$A$201)=12)*(YEAR('Daily Expenses'!$A$2:$A$201)=YEAR(TODAY()))*('Daily Expenses'!$C$2:$C$201="Meat"))
A22: Fish | B22: =SUMPRODUCT(('Daily Expenses'!$G$2:$G$201)*(MONTH('Daily Expenses'!$A$2:$A$201)=1)*(YEAR('Daily Expenses'!$A$2:$A$201)=YEAR(TODAY()))*('Daily Expenses'!$C$2:$C$201="Fish")) | C22: =SUMPRODUCT(('Daily Expenses'!$G$2:$G$201)*(MONTH('Daily Expenses'!$A$2:$A$201)=2)*(YEAR('Daily Expenses'!$A$2:$A$201)=YEAR(TODAY()))*('Daily Expenses'!$C$2:$C$201="Fish")) | D22: =SUMPRODUCT(('Daily Expenses'!$G$2:$G$201)*(MONTH('Daily Expenses'!$A$2:$A$201)=3)*(YEAR('Daily Expenses'!$A$2:$A$201)=YEAR(TODAY()))*('Daily Expenses'!$C$2:$C$201="Fish")) | E22: =SUMPRODUCT(('Daily Expenses'!$G$2:$G$201)*(MONTH('Daily Expenses'!$A$2:$A$201)=4)*(YEAR('Daily Expenses'!$A$2:$A$201)=YEAR(TODAY()))*('Daily Expenses'!$C$2:$C$201="Fish")) | F22: =SUMPRODUCT(('Daily Expenses'!$G$2:$G$201)*(MONTH('Daily Expenses'!$A$2:$A$201)=5)*(YEAR('Daily Expenses'!$A$2:$A$201)=YEAR(TODAY()))*('Daily Expenses'!$C$2:$C$201="Fish")) | G22: =SUMPRODUCT(('Daily Expenses'!$G$2:$G$201)*(MONTH('Daily Expenses'!$A$2:$A$201)=6)*(YEAR('Daily Expenses'!$A$2:$A$201)=YEAR(TODAY()))*('Daily Expenses'!$C$2:$C$201="Fish")) | H22: =SUMPRODUCT(('Daily Expenses'!$G$2:$G$201)*(MONTH('Daily Expenses'!$A$2:$A$201)=7)*(YEAR('Daily Expenses'!$A$2:$A$201)=YEAR(TODAY()))*('Daily Expenses'!$C$2:$C$201="Fish")) | I22: =SUMPRODUCT(('Daily Expenses'!$G$2:$G$201)*(MONTH('Daily Expenses'!$A$2:$A$201)=8)*(YEAR('Daily Expenses'!$A$2:$A$201)=YEAR(TODAY()))*('Daily Expenses'!$C$2:$C$201="Fish")) | J22: =SUMPRODUCT(('Daily Expenses'!$G$2:$G$201)*(MONTH('Daily Expenses'!$A$2:$A$201)=9)*(YEAR('Daily Expenses'!$A$2:$A$201)=YEAR(TODAY()))*('Daily Expenses'!$C$2:$C$201="Fish")) | K22: =SUMPRODUCT(('Daily Expenses'!$G$2:$G$201)*(MONTH('Daily Expenses'!$A$2:$A$201)=10)*(YEAR('Daily Expenses'!$A$2:$A$201)=YEAR(TODAY()))*('Daily Expenses'!$C$2:$C$201="Fish")) | L22: =SUMPRODUCT(('Daily Expenses'!$G$2:$G$201)*(MONTH('Daily Expenses'!$A$2:$A$201)=11)*(YEAR('Daily Expenses'!$A$2:$A$201)=YEAR(TODAY()))*('Daily Expenses'!$C$2:$C$201="Fish")) | M22: =SUMPRODUCT(('Daily Expenses'!$G$2:$G$201)*(MONTH('Daily Expenses'!$A$2:$A$201)=12)*(YEAR('Daily Expenses'!$A$2:$A$201)=YEAR(TODAY()))*('Daily Expenses'!$C$2:$C$201="Fish"))
A23: Protein | B23: =SUMPRODUCT(('Daily Expenses'!$G$2:$G$201)*(MONTH('Daily Expenses'!$A$2:$A$201)=1)*(YEAR('Daily Expenses'!$A$2:$A$201)=YEAR(TODAY()))*('Daily Expenses'!$C$2:$C$201="Protein")) | C23: =SUMPRODUCT(('Daily Expenses'!$G$2:$G$201)*(MONTH('Daily Expenses'!$A$2:$A$201)=2)*(YEAR('Daily Expenses'!$A$2:$A$201)=YEAR(TODAY()))*('Daily Expenses'!$C$2:$C$201="Protein")) | D23: =SUMPRODUCT(('Daily Expenses'!$G$2:$G$201)*(MONTH('Daily Expenses'!$A$2:$A$201)=3)*(YEAR('Daily Expenses'!$A$2:$A$201)=YEAR(TODAY()))*('Daily Expenses'!$C$2:$C$201="Protein")) | E23: =SUMPRODUCT(('Daily Expenses'!$G$2:$G$201)*(MONTH('Daily Expenses'!$A$2:$A$201)=4)*(YEAR('Daily Expenses'!$A$2:$A$201)=YEAR(TODAY()))*('Daily Expenses'!$C$2:$C$201="Protein")) | F23: =SUMPRODUCT(('Daily Expenses'!$G$2:$G$201)*(MONTH('Daily Expenses'!$A$2:$A$201)=5)*(YEAR('Daily Expenses'!$A$2:$A$201)=YEAR(TODAY()))*('Daily Expenses'!$C$2:$C$201="Protein")) | G23: =SUMPRODUCT(('Daily Expenses'!$G$2:$G$201)*(MONTH('Daily Expenses'!$A$2:$A$201)=6)*(YEAR('Daily Expenses'!$A$2:$A$201)=YEAR(TODAY()))*('Daily Expenses'!$C$2:$C$201="Protein")) | H23: =SUMPRODUCT(('Daily Expenses'!$G$2:$G$201)*(MONTH('Daily Expenses'!$A$2:$A$201)=7)*(YEAR('Daily Expenses'!$A$2:$A$201)=YEAR(TODAY()))*('Daily Expenses'!$C$2:$C$201="Protein")) | I23: =SUMPRODUCT(('Daily Expenses'!$G$2:$G$201)*(MONTH('Daily Expenses'!$A$2:$A$201)=8)*(YEAR('Daily Expenses'!$A$2:$A$201)=YEAR(TODAY()))*('Daily Expenses'!$C$2:$C$201="Protein")) | J23: =SUMPRODUCT(('Daily Expenses'!$G$2:$G$201)*(MONTH('Daily Expenses'!$A$2:$A$201)=9)*(YEAR('Daily Expenses'!$A$2:$A$201)=YEAR(TODAY()))*('Daily Expenses'!$C$2:$C$201="Protein")) | K23: =SUMPRODUCT(('Daily Expenses'!$G$2:$G$201)*(MONTH('Daily Expenses'!$A$2:$A$201)=10)*(YEAR('Daily Expenses'!$A$2:$A$201)=YEAR(TODAY()))*('Daily Expenses'!$C$2:$C$201="Protein")) | L23: =SUMPRODUCT(('Daily Expenses'!$G$2:$G$201)*(MONTH('Daily Expenses'!$A$2:$A$201)=11)*(YEAR('Daily Expenses'!$A$2:$A$201)=YEAR(TODAY()))*('Daily Expenses'!$C$2:$C$201="Protein")) | M23: =SUMPRODUCT(('Daily Expenses'!$G$2:$G$201)*(MONTH('Daily Expenses'!$A$2:$A$201)=12)*(YEAR('Daily Expenses'!$A$2:$A$201)=YEAR(TODAY()))*('Daily Expenses'!$C$2:$C$201="Protein"))
A24: Snacks | B24: =SUMPRODUCT(('Daily Expenses'!$G$2:$G$201)*(MONTH('Daily Expenses'!$A$2:$A$201)=1)*(YEAR('Daily Expenses'!$A$2:$A$201)=YEAR(TODAY()))*('Daily Expenses'!$C$2:$C$201="Snacks")) | C24: =SUMPRODUCT(('Daily Expenses'!$G$2:$G$201)*(MONTH('Daily Expenses'!$A$2:$A$201)=2)*(YEAR('Daily Expenses'!$A$2:$A$201)=YEAR(TODAY()))*('Daily Expenses'!$C$2:$C$201="Snacks")) | D24: =SUMPRODUCT(('Daily Expenses'!$G$2:$G$201)*(MONTH('Daily Expenses'!$A$2:$A$201)=3)*(YEAR('Daily Expenses'!$A$2:$A$201)=YEAR(TODAY()))*('Daily Expenses'!$C$2:$C$201="Snacks")) | E24: =SUMPRODUCT(('Daily Expenses'!$G$2:$G$201)*(MONTH('Daily Expenses'!$A$2:$A$201)=4)*(YEAR('Daily Expenses'!$A$2:$A$201)=YEAR(TODAY()))*('Daily Expenses'!$C$2:$C$201="Snacks")) | F24: =SUMPRODUCT(('Daily Expenses'!$G$2:$G$201)*(MONTH('Daily Expenses'!$A$2:$A$201)=5)*(YEAR('Daily Expenses'!$A$2:$A$201)=YEAR(TODAY()))*('Daily Expenses'!$C$2:$C$201="Snacks")) | G24: =SUMPRODUCT(('Daily Expenses'!$G$2:$G$201)*(MONTH('Daily Expenses'!$A$2:$A$201)=6)*(YEAR('Daily Expenses'!$A$2:$A$201)=YEAR(TODAY()))*('Daily Expenses'!$C$2:$C$201="Snacks")) | H24: =SUMPRODUCT(('Daily Expenses'!$G$2:$G$201)*(MONTH('Daily Expenses'!$A$2:$A$201)=7)*(YEAR('Daily Expenses'!$A$2:$A$201)=YEAR(TODAY()))*('Daily Expenses'!$C$2:$C$201="Snacks")) | I24: =SUMPRODUCT(('Daily Expenses'!$G$2:$G$201)*(MONTH('Daily Expenses'!$A$2:$A$201)=8)*(YEAR('Daily Expenses'!$A$2:$A$201)=YEAR(TODAY()))*('Daily Expenses'!$C$2:$C$201="Snacks")) | J24: =SUMPRODUCT(('Daily Expenses'!$G$2:$G$201)*(MONTH('Daily Expenses'!$A$2:$A$201)=9)*(YEAR('Daily Expenses'!$A$2:$A$201)=YEAR(TODAY()))*('Daily Expenses'!$C$2:$C$201="Snacks")) | K24: =SUMPRODUCT(('Daily Expenses'!$G$2:$G$201)*(MONTH('Daily Expenses'!$A$2:$A$201)=10)*(YEAR('Daily Expenses'!$A$2:$A$201)=YEAR(TODAY()))*('Daily Expenses'!$C$2:$C$201="Snacks")) | L24: =SUMPRODUCT(('Daily Expenses'!$G$2:$G$201)*(MONTH('Daily Expenses'!$A$2:$A$201)=11)*(YEAR('Daily Expenses'!$A$2:$A$201)=YEAR(TODAY()))*('Daily Expenses'!$C$2:$C$201="Snacks")) | M24: =SUMPRODUCT(('Daily Expenses'!$G$2:$G$201)*(MONTH('Daily Expenses'!$A$2:$A$201)=12)*(YEAR('Daily Expenses'!$A$2:$A$201)=YEAR(TODAY()))*('Daily Expenses'!$C$2:$C$201="Snacks"))
A25: Drinks | B25: =SUMPRODUCT(('Daily Expenses'!$G$2:$G$201)*(MONTH('Daily Expenses'!$A$2:$A$201)=1)*(YEAR('Daily Expenses'!$A$2:$A$201)=YEAR(TODAY()))*('Daily Expenses'!$C$2:$C$201="Drinks")) | C25: =SUMPRODUCT(('Daily Expenses'!$G$2:$G$201)*(MONTH('Daily Expenses'!$A$2:$A$201)=2)*(YEAR('Daily Expenses'!$A$2:$A$201)=YEAR(TODAY()))*('Daily Expenses'!$C$2:$C$201="Drinks")) | D25: =SUMPRODUCT(('Daily Expenses'!$G$2:$G$201)*(MONTH('Daily Expenses'!$A$2:$A$201)=3)*(YEAR('Daily Expenses'!$A$2:$A$201)=YEAR(TODAY()))*('Daily Expenses'!$C$2:$C$201="Drinks")) | E25: =SUMPRODUCT(('Daily Expenses'!$G$2:$G$201)*(MONTH('Daily Expenses'!$A$2:$A$201)=4)*(YEAR('Daily Expenses'!$A$2:$A$201)=YEAR(TODAY()))*('Daily Expenses'!$C$2:$C$201="Drinks")) | F25: =SUMPRODUCT(('Daily Expenses'!$G$2:$G$201)*(MONTH('Daily Expenses'!$A$2:$A$201)=5)*(YEAR('Daily Expenses'!$A$2:$A$201)=YEAR(TODAY()))*('Daily Expenses'!$C$2:$C$201="Drinks")) | G25: =SUMPRODUCT(('Daily Expenses'!$G$2:$G$201)*(MONTH('Daily Expenses'!$A$2:$A$201)=6)*(YEAR('Daily Expenses'!$A$2:$A$201)=YEAR(TODAY()))*('Daily Expenses'!$C$2:$C$201="Drinks")) | H25: =SUMPRODUCT(('Daily Expenses'!$G$2:$G$201)*(MONTH('Daily Expenses'!$A$2:$A$201)=7)*(YEAR('Daily Expenses'!$A$2:$A$201)=YEAR(TODAY()))*('Daily Expenses'!$C$2:$C$201="Drinks")) | I25: =SUMPRODUCT(('Daily Expenses'!$G$2:$G$201)*(MONTH('Daily Expenses'!$A$2:$A$201)=8)*(YEAR('Daily Expenses'!$A$2:$A$201)=YEAR(TODAY()))*('Daily Expenses'!$C$2:$C$201="Drinks")) | J25: =SUMPRODUCT(('Daily Expenses'!$G$2:$G$201)*(MONTH('Daily Expenses'!$A$2:$A$201)=9)*(YEAR('Daily Expenses'!$A$2:$A$201)=YEAR(TODAY()))*('Daily Expenses'!$C$2:$C$201="Drinks")) | K25: =SUMPRODUCT(('Daily Expenses'!$G$2:$G$201)*(MONTH('Daily Expenses'!$A$2:$A$201)=10)*(YEAR('Daily Expenses'!$A$2:$A$201)=YEAR(TODAY()))*('Daily Expenses'!$C$2:$C$201="Drinks")) | L25: =SUMPRODUCT(('Daily Expenses'!$G$2:$G$201)*(MONTH('Daily Expenses'!$A$2:$A$201)=11)*(YEAR('Daily Expenses'!$A$2:$A$201)=YEAR(TODAY()))*('Daily Expenses'!$C$2:$C$201="Drinks")) | M25: =SUMPRODUCT(('Daily Expenses'!$G$2:$G$201)*(MONTH('Daily Expenses'!$A$2:$A$201)=12)*(YEAR('Daily Expenses'!$A$2:$A$201)=YEAR(TODAY()))*('Daily Expenses'!$C$2:$C$201="Drinks"))
A26: Transport | B26: =SUMPRODUCT(('Daily Expenses'!$G$2:$G$201)*(MONTH('Daily Expenses'!$A$2:$A$201)=1)*(YEAR('Daily Expenses'!$A$2:$A$201)=YEAR(TODAY()))*('Daily Expenses'!$C$2:$C$201="Transport")) | C26: =SUMPRODUCT(('Daily Expenses'!$G$2:$G$201)*(MONTH('Daily Expenses'!$A$2:$A$201)=2)*(YEAR('Daily Expenses'!$A$2:$A$201)=YEAR(TODAY()))*('Daily Expenses'!$C$2:$C$201="Transport")) | D26: =SUMPRODUCT(('Daily Expenses'!$G$2:$G$201)*(MONTH('Daily Expenses'!$A$2:$A$201)=3)*(YEAR('Daily Expenses'!$A$2:$A$201)=YEAR(TODAY()))*('Daily Expenses'!$C$2:$C$201="Transport")) | E26: =SUMPRODUCT(('Daily Expenses'!$G$2:$G$201)*(MONTH('Daily Expenses'!$A$2:$A$201)=4)*(YEAR('Daily Expenses'!$A$2:$A$201)=YEAR(TODAY()))*('Daily Expenses'!$C$2:$C$201="Transport")) | F26: =SUMPRODUCT(('Daily Expenses'!$G$2:$G$201)*(MONTH('Daily Expenses'!$A$2:$A$201)=5)*(YEAR('Daily Expenses'!$A$2:$A$201)=YEAR(TODAY()))*('Daily Expenses'!$C$2:$C$201="Transport")) | G26: =SUMPRODUCT(('Daily Expenses'!$G$2:$G$201)*(MONTH('Daily Expenses'!$A$2:$A$201)=6)*(YEAR('Daily Expenses'!$A$2:$A$201)=YEAR(TODAY()))*('Daily Expenses'!$C$2:$C$201="Transport")) | H26: =SUMPRODUCT(('Daily Expenses'!$G$2:$G$201)*(MONTH('Daily Expenses'!$A$2:$A$201)=7)*(YEAR('Daily Expenses'!$A$2:$A$201)=YEAR(TODAY()))*('Daily Expenses'!$C$2:$C$201="Transport")) | I26: =SUMPRODUCT(('Daily Expenses'!$G$2:$G$201)*(MONTH('Daily Expenses'!$A$2:$A$201)=8)*(YEAR('Daily Expenses'!$A$2:$A$201)=YEAR(TODAY()))*('Daily Expenses'!$C$2:$C$201="Transport")) | J26: =SUMPRODUCT(('Daily Expenses'!$G$2:$G$201)*(MONTH('Daily Expenses'!$A$2:$A$201)=9)*(YEAR('Daily Expenses'!$A$2:$A$201)=YEAR(TODAY()))*('Daily Expenses'!$C$2:$C$201="Transport")) | K26: =SUMPRODUCT(('Daily Expenses'!$G$2:$G$201)*(MONTH('Daily Expenses'!$A$2:$A$201)=10)*(YEAR('Daily Expenses'!$A$2:$A$201)=YEAR(TODAY()))*('Daily Expenses'!$C$2:$C$201="Transport")) | L26: =SUMPRODUCT(('Daily Expenses'!$G$2:$G$201)*(MONTH('Daily Expenses'!$A$2:$A$201)=11)*(YEAR('Daily Expenses'!$A$2:$A$201)=YEAR(TODAY()))*('Daily Expenses'!$C$2:$C$201="Transport")) | M26: =SUMPRODUCT(('Daily Expenses'!$G$2:$G$201)*(MONTH('Daily Expenses'!$A$2:$A$201)=12)*(YEAR('Daily Expenses'!$A$2:$A$201)=YEAR(TODAY()))*('Daily Expenses'!$C$2:$C$201="Transport"))
A27: Health | B27: =SUMPRODUCT(('Daily Expenses'!$G$2:$G$201)*(MONTH('Daily Expenses'!$A$2:$A$201)=1)*(YEAR('Daily Expenses'!$A$2:$A$201)=YEAR(TODAY()))*('Daily Expenses'!$C$2:$C$201="Health")) | C27: =SUMPRODUCT(('Daily Expenses'!$G$2:$G$201)*(MONTH('Daily Expenses'!$A$2:$A$201)=2)*(YEAR('Daily Expenses'!$A$2:$A$201)=YEAR(TODAY()))*('Daily Expenses'!$C$2:$C$201="Health")) | D27: =SUMPRODUCT(('Daily Expenses'!$G$2:$G$201)*(MONTH('Daily Expenses'!$A$2:$A$201)=3)*(YEAR('Daily Expenses'!$A$2:$A$201)=YEAR(TODAY()))*('Daily Expenses'!$C$2:$C$201="Health")) | E27: =SUMPRODUCT(('Daily Expenses'!$G$2:$G$201)*(MONTH('Daily Expenses'!$A$2:$A$201)=4)*(YEAR('Daily Expenses'!$A$2:$A$201)=YEAR(TODAY()))*('Daily Expenses'!$C$2:$C$201="Health")) | F27: =SUMPRODUCT(('Daily Expenses'!$G$2:$G$201)*(MONTH('Daily Expenses'!$A$2:$A$201)=5)*(YEAR('Daily Expenses'!$A$2:$A$201)=YEAR(TODAY()))*('Daily Expenses'!$C$2:$C$201="Health")) | G27: =SUMPRODUCT(('Daily Expenses'!$G$2:$G$201)*(MONTH('Daily Expenses'!$A$2:$A$201)=6)*(YEAR('Daily Expenses'!$A$2:$A$201)=YEAR(TODAY()))*('Daily Expenses'!$C$2:$C$201="Health")) | H27: =SUMPRODUCT(('Daily Expenses'!$G$2:$G$201)*(MONTH('Daily Expenses'!$A$2:$A$201)=7)*(YEAR('Daily Expenses'!$A$2:$A$201)=YEAR(TODAY()))*('Daily Expenses'!$C$2:$C$201="Health")) | I27: =SUMPRODUCT(('Daily Expenses'!$G$2:$G$201)*(MONTH('Daily Expenses'!$A$2:$A$201)=8)*(YEAR('Daily Expenses'!$A$2:$A$201)=YEAR(TODAY()))*('Daily Expenses'!$C$2:$C$201="Health")) | J27: =SUMPRODUCT(('Daily Expenses'!$G$2:$G$201)*(MONTH('Daily Expenses'!$A$2:$A$201)=9)*(YEAR('Daily Expenses'!$A$2:$A$201)=YEAR(TODAY()))*('Daily Expenses'!$C$2:$C$201="Health")) | K27: =SUMPRODUCT(('Daily Expenses'!$G$2:$G$201)*(MONTH('Daily Expenses'!$A$2:$A$201)=10)*(YEAR('Daily Expenses'!$A$2:$A$201)=YEAR(TODAY()))*('Daily Expenses'!$C$2:$C$201="Health")) | L27: =SUMPRODUCT(('Daily Expenses'!$G$2:$G$201)*(MONTH('Daily Expenses'!$A$2:$A$201)=11)*(YEAR('Daily Expenses'!$A$2:$A$201)=YEAR(TODAY()))*('Daily Expenses'!$C$2:$C$201="Health")) | M27: =SUMPRODUCT(('Daily Expenses'!$G$2:$G$201)*(MONTH('Daily Expenses'!$A$2:$A$201)=12)*(YEAR('Daily Expenses'!$A$2:$A$201)=YEAR(TODAY()))*('Daily Expenses'!$C$2:$C$201="Health"))
A28: Supplements | B28: =SUMPRODUCT(('Daily Expenses'!$G$2:$G$201)*(MONTH('Daily Expenses'!$A$2:$A$201)=1)*(YEAR('Daily Expenses'!$A$2:$A$201)=YEAR(TODAY()))*('Daily Expenses'!$C$2:$C$201="Supplements")) | C28: =SUMPRODUCT(('Daily Expenses'!$G$2:$G$201)*(MONTH('Daily Expenses'!$A$2:$A$201)=2)*(YEAR('Daily Expenses'!$A$2:$A$201)=YEAR(TODAY()))*('Daily Expenses'!$C$2:$C$201="Supplements")) | D28: =SUMPRODUCT(('Daily Expenses'!$G$2:$G$201)*(MONTH('Daily Expenses'!$A$2:$A$201)=3)*(YEAR('Daily Expenses'!$A$2:$A$201)=YEAR(TODAY()))*('Daily Expenses'!$C$2:$C$201="Supplements")) | E28: =SUMPRODUCT(('Daily Expenses'!$G$2:$G$201)*(MONTH('Daily Expenses'!$A$2:$A$201)=4)*(YEAR('Daily Expenses'!$A$2:$A$201)=YEAR(TODAY()))*('Daily Expenses'!$C$2:$C$201="Supplements")) | F28: =SUMPRODUCT(('Daily Expenses'!$G$2:$G$201)*(MONTH('Daily Expenses'!$A$2:$A$201)=5)*(YEAR('Daily Expenses'!$A$2:$A$201)=YEAR(TODAY()))*('Daily Expenses'!$C$2:$C$201="Supplements")) | G28: =SUMPRODUCT(('Daily Expenses'!$G$2:$G$201)*(MONTH('Daily Expenses'!$A$2:$A$201)=6)*(YEAR('Daily Expenses'!$A$2:$A$201)=YEAR(TODAY()))*('Daily Expenses'!$C$2:$C$201="Supplements")) | H28: =SUMPRODUCT(('Daily Expenses'!$G$2:$G$201)*(MONTH('Daily Expenses'!$A$2:$A$201)=7)*(YEAR('Daily Expenses'!$A$2:$A$201)=YEAR(TODAY()))*('Daily Expenses'!$C$2:$C$201="Supplements")) | I28: =SUMPRODUCT(('Daily Expenses'!$G$2:$G$201)*(MONTH('Daily Expenses'!$A$2:$A$201)=8)*(YEAR('Daily Expenses'!$A$2:$A$201)=YEAR(TODAY()))*('Daily Expenses'!$C$2:$C$201="Supplements")) | J28: =SUMPRODUCT(('Daily Expenses'!$G$2:$G$201)*(MONTH('Daily Expenses'!$A$2:$A$201)=9)*(YEAR('Daily Expenses'!$A$2:$A$201)=YEAR(TODAY()))*('Daily Expenses'!$C$2:$C$201="Supplements")) | K28: =SUMPRODUCT(('Daily Expenses'!$G$2:$G$201)*(MONTH('Daily Expenses'!$A$2:$A$201)=10)*(YEAR('Daily Expenses'!$A$2:$A$201)=YEAR(TODAY()))*('Daily Expenses'!$C$2:$C$201="Supplements")) | L28: =SUMPRODUCT(('Daily Expenses'!$G$2:$G$201)*(MONTH('Daily Expenses'!$A$2:$A$201)=11)*(YEAR('Daily Expenses'!$A$2:$A$201)=YEAR(TODAY()))*('Daily Expenses'!$C$2:$C$201="Supplements")) | M28: =SUMPRODUCT(('Daily Expenses'!$G$2:$G$201)*(MONTH('Daily Expenses'!$A$2:$A$201)=12)*(YEAR('Daily Expenses'!$A$2:$A$201)=YEAR(TODAY()))*('Daily Expenses'!$C$2:$C$201="Supplements"))
A29: Household | B29: =SUMPRODUCT(('Daily Expenses'!$G$2:$G$201)*(MONTH('Daily Expenses'!$A$2:$A$201)=1)*(YEAR('Daily Expenses'!$A$2:$A$201)=YEAR(TODAY()))*('Daily Expenses'!$C$2:$C$201="Household")) | C29: =SUMPRODUCT(('Daily Expenses'!$G$2:$G$201)*(MONTH('Daily Expenses'!$A$2:$A$201)=2)*(YEAR('Daily Expenses'!$A$2:$A$201)=YEAR(TODAY()))*('Daily Expenses'!$C$2:$C$201="Household")) | D29: =SUMPRODUCT(('Daily Expenses'!$G$2:$G$201)*(MONTH('Daily Expenses'!$A$2:$A$201)=3)*(YEAR('Daily Expenses'!$A$2:$A$201)=YEAR(TODAY()))*('Daily Expenses'!$C$2:$C$201="Household")) | E29: =SUMPRODUCT(('Daily Expenses'!$G$2:$G$201)*(MONTH('Daily Expenses'!$A$2:$A$201)=4)*(YEAR('Daily Expenses'!$A$2:$A$201)=YEAR(TODAY()))*('Daily Expenses'!$C$2:$C$201="Household")) | F29: =SUMPRODUCT(('Daily Expenses'!$G$2:$G$201)*(MONTH('Daily Expenses'!$A$2:$A$201)=5)*(YEAR('Daily Expenses'!$A$2:$A$201)=YEAR(TODAY()))*('Daily Expenses'!$C$2:$C$201="Household")) | G29: =SUMPRODUCT(('Daily Expenses'!$G$2:$G$201)*(MONTH('Daily Expenses'!$A$2:$A$201)=6)*(YEAR('Daily Expenses'!$A$2:$A$201)=YEAR(TODAY()))*('Daily Expenses'!$C$2:$C$201="Household")) | H29: =SUMPRODUCT(('Daily Expenses'!$G$2:$G$201)*(MONTH('Daily Expenses'!$A$2:$A$201)=7)*(YEAR('Daily Expenses'!$A$2:$A$201)=YEAR(TODAY()))*('Daily Expenses'!$C$2:$C$201="Household")) | I29: =SUMPRODUCT(('Daily Expenses'!$G$2:$G$201)*(MONTH('Daily Expenses'!$A$2:$A$201)=8)*(YEAR('Daily Expenses'!$A$2:$A$201)=YEAR(TODAY()))*('Daily Expenses'!$C$2:$C$201="Household")) | J29: =SUMPRODUCT(('Daily Expenses'!$G$2:$G$201)*(MONTH('Daily Expenses'!$A$2:$A$201)=9)*(YEAR('Daily Expenses'!$A$2:$A$201)=YEAR(TODAY()))*('Daily Expenses'!$C$2:$C$201="Household")) | K29: =SUMPRODUCT(('Daily Expenses'!$G$2:$G$201)*(MONTH('Daily Expenses'!$A$2:$A$201)=10)*(YEAR('Daily Expenses'!$A$2:$A$201)=YEAR(TODAY()))*('Daily Expenses'!$C$2:$C$201="Household")) | L29: =SUMPRODUCT(('Daily Expenses'!$G$2:$G$201)*(MONTH('Daily Expenses'!$A$2:$A$201)=11)*(YEAR('Daily Expenses'!$A$2:$A$201)=YEAR(TODAY()))*('Daily Expenses'!$C$2:$C$201="Household")) | M29: =SUMPRODUCT(('Daily Expenses'!$G$2:$G$201)*(MONTH('Daily Expenses'!$A$2:$A$201)=12)*(YEAR('Daily Expenses'!$A$2:$A$201)=YEAR(TODAY()))*('Daily Expenses'!$C$2:$C$201="Household"))
A30: Electronics | B30: =SUMPRODUCT(('Daily Expenses'!$G$2:$G$201)*(MONTH('Daily Expenses'!$A$2:$A$201)=1)*(YEAR('Daily Expenses'!$A$2:$A$201)=YEAR(TODAY()))*('Daily Expenses'!$C$2:$C$201="Electronics")) | C30: =SUMPRODUCT(('Daily Expenses'!$G$2:$G$201)*(MONTH('Daily Expenses'!$A$2:$A$201)=2)*(YEAR('Daily Expenses'!$A$2:$A$201)=YEAR(TODAY()))*('Daily Expenses'!$C$2:$C$201="Electronics")) | D30: =SUMPRODUCT(('Daily Expenses'!$G$2:$G$201)*(MONTH('Daily Expenses'!$A$2:$A$201)=3)*(YEAR('Daily Expenses'!$A$2:$A$201)=YEAR(TODAY()))*('Daily Expenses'!$C$2:$C$201="Electronics")) | E30: =SUMPRODUCT(('Daily Expenses'!$G$2:$G$201)*(MONTH('Daily Expenses'!$A$2:$A$201)=4)*(YEAR('Daily Expenses'!$A$2:$A$201)=YEAR(TODAY()))*('Daily Expenses'!$C$2:$C$201="Electronics")) | F30: =SUMPRODUCT(('Daily Expenses'!$G$2:$G$201)*(MONTH('Daily Expenses'!$A$2:$A$201)=5)*(YEAR('Daily Expenses'!$A$2:$A$201)=YEAR(TODAY()))*('Daily Expenses'!$C$2:$C$201="Electronics")) | G30: =SUMPRODUCT(('Daily Expenses'!$G$2:$G$201)*(MONTH('Daily Expenses'!$A$2:$A$201)=6)*(YEAR('Daily Expenses'!$A$2:$A$201)=YEAR(TODAY()))*('Daily Expenses'!$C$2:$C$201="Electronics")) | H30: =SUMPRODUCT(('Daily Expenses'!$G$2:$G$201)*(MONTH('Daily Expenses'!$A$2:$A$201)=7)*(YEAR('Daily Expenses'!$A$2:$A$201)=YEAR(TODAY()))*('Daily Expenses'!$C$2:$C$201="Electronics")) | I30: =SUMPRODUCT(('Daily Expenses'!$G$2:$G$201)*(MONTH('Daily Expenses'!$A$2:$A$201)=8)*(YEAR('Daily Expenses'!$A$2:$A$201)=YEAR(TODAY()))*('Daily Expenses'!$C$2:$C$201="Electronics")) | J30: =SUMPRODUCT(('Daily Expenses'!$G$2:$G$201)*(MONTH('Daily Expenses'!$A$2:$A$201)=9)*(YEAR('Daily Expenses'!$A$2:$A$201)=YEAR(TODAY()))*('Daily Expenses'!$C$2:$C$201="Electronics")) | K30: =SUMPRODUCT(('Daily Expenses'!$G$2:$G$201)*(MONTH('Daily Expenses'!$A$2:$A$201)=10)*(YEAR('Daily Expenses'!$A$2:$A$201)=YEAR(TODAY()))*('Daily Expenses'!$C$2:$C$201="Electronics")) | L30: =SUMPRODUCT(('Daily Expenses'!$G$2:$G$201)*(MONTH('Daily Expenses'!$A$2:$A$201)=11)*(YEAR('Daily Expenses'!$A$2:$A$201)=YEAR(TODAY()))*('Daily Expenses'!$C$2:$C$201="Electronics")) | M30: =SUMPRODUCT(('Daily Expenses'!$G$2:$G$201)*(MONTH('Daily Expenses'!$A$2:$A$201)=12)*(YEAR('Daily Expenses'!$A$2:$A$201)=YEAR(TODAY()))*('Daily Expenses'!$C$2:$C$201="Electronics"))
A31: Clothing | B31: =SUMPRODUCT(('Daily Expenses'!$G$2:$G$201)*(MONTH('Daily Expenses'!$A$2:$A$201)=1)*(YEAR('Daily Expenses'!$A$2:$A$201)=YEAR(TODAY()))*('Daily Expenses'!$C$2:$C$201="Clothing")) | C31: =SUMPRODUCT(('Daily Expenses'!$G$2:$G$201)*(MONTH('Daily Expenses'!$A$2:$A$201)=2)*(YEAR('Daily Expenses'!$A$2:$A$201)=YEAR(TODAY()))*('Daily Expenses'!$C$2:$C$201="Clothing")) | D31: =SUMPRODUCT(('Daily Expenses'!$G$2:$G$201)*(MONTH('Daily Expenses'!$A$2:$A$201)=3)*(YEAR('Daily Expenses'!$A$2:$A$201)=YEAR(TODAY()))*('Daily Expenses'!$C$2:$C$201="Clothing")) | E31: =SUMPRODUCT(('Daily Expenses'!$G$2:$G$201)*(MONTH('Daily Expenses'!$A$2:$A$201)=4)*(YEAR('Daily Expenses'!$A$2:$A$201)=YEAR(TODAY()))*('Daily Expenses'!$C$2:$C$201="Clothing")) | F31: =SUMPRODUCT(('Daily Expenses'!$G$2:$G$201)*(MONTH('Daily Expenses'!$A$2:$A$201)=5)*(YEAR('Daily Expenses'!$A$2:$A$201)=YEAR(TODAY()))*('Daily Expenses'!$C$2:$C$201="Clothing")) | G31: =SUMPRODUCT(('Daily Expenses'!$G$2:$G$201)*(MONTH('Daily Expenses'!$A$2:$A$201)=6)*(YEAR('Daily Expenses'!$A$2:$A$201)=YEAR(TODAY()))*('Daily Expenses'!$C$2:$C$201="Clothing")) | H31: =SUMPRODUCT(('Daily Expenses'!$G$2:$G$201)*(MONTH('Daily Expenses'!$A$2:$A$201)=7)*(YEAR('Daily Expenses'!$A$2:$A$201)=YEAR(TODAY()))*('Daily Expenses'!$C$2:$C$201="Clothing")) | I31: =SUMPRODUCT(('Daily Expenses'!$G$2:$G$201)*(MONTH('Daily Expenses'!$A$2:$A$201)=8)*(YEAR('Daily Expenses'!$A$2:$A$201)=YEAR(TODAY()))*('Daily Expenses'!$C$2:$C$201="Clothing")) | J31: =SUMPRODUCT(('Daily Expenses'!$G$2:$G$201)*(MONTH('Daily Expenses'!$A$2:$A$201)=9)*(YEAR('Daily Expenses'!$A$2:$A$201)=YEAR(TODAY()))*('Daily Expenses'!$C$2:$C$201="Clothing")) | K31: =SUMPRODUCT(('Daily Expenses'!$G$2:$G$201)*(MONTH('Daily Expenses'!$A$2:$A$201)=10)*(YEAR('Daily Expenses'!$A$2:$A$201)=YEAR(TODAY()))*('Daily Expenses'!$C$2:$C$201="Clothing")) | L31: =SUMPRODUCT(('Daily Expenses'!$G$2:$G$201)*(MONTH('Daily Expenses'!$A$2:$A$201)=11)*(YEAR('Daily Expenses'!$A$2:$A$201)=YEAR(TODAY()))*('Daily Expenses'!$C$2:$C$201="Clothing")) | M31: =SUMPRODUCT(('Daily Expenses'!$G$2:$G$201)*(MONTH('Daily Expenses'!$A$2:$A$201)=12)*(YEAR('Daily Expenses'!$A$2:$A$201)=YEAR(TODAY()))*('Daily Expenses'!$C$2:$C$201="Clothing"))
A32: Entertainment | B32: =SUMPRODUCT(('Daily Expenses'!$G$2:$G$201)*(MONTH('Daily Expenses'!$A$2:$A$201)=1)*(YEAR('Daily Expenses'!$A$2:$A$201)=YEAR(TODAY()))*('Daily Expenses'!$C$2:$C$201="Entertainment")) | C32: =SUMPRODUCT(('Daily Expenses'!$G$2:$G$201)*(MONTH('Daily Expenses'!$A$2:$A$201)=2)*(YEAR('Daily Expenses'!$A$2:$A$201)=YEAR(TODAY()))*('Daily Expenses'!$C$2:$C$201="Entertainment")) | D32: =SUMPRODUCT(('Daily Expenses'!$G$2:$G$201)*(MONTH('Daily Expenses'!$A$2:$A$201)=3)*(YEAR('Daily Expenses'!$A$2:$A$201)=YEAR(TODAY()))*('Daily Expenses'!$C$2:$C$201="Entertainment")) | E32: =SUMPRODUCT(('Daily Expenses'!$G$2:$G$201)*(MONTH('Daily Expenses'!$A$2:$A$201)=4)*(YEAR('Daily Expenses'!$A$2:$A$201)=YEAR(TODAY()))*('Daily Expenses'!$C$2:$C$201="Entertainment")) | F32: =SUMPRODUCT(('Daily Expenses'!$G$2:$G$201)*(MONTH('Daily Expenses'!$A$2:$A$201)=5)*(YEAR('Daily Expenses'!$A$2:$A$201)=YEAR(TODAY()))*('Daily Expenses'!$C$2:$C$201="Entertainment")) | G32: =SUMPRODUCT(('Daily Expenses'!$G$2:$G$201)*(MONTH('Daily Expenses'!$A$2:$A$201)=6)*(YEAR('Daily Expenses'!$A$2:$A$201)=YEAR(TODAY()))*('Daily Expenses'!$C$2:$C$201="Entertainment")) | H32: =SUMPRODUCT(('Daily Expenses'!$G$2:$G$201)*(MONTH('Daily Expenses'!$A$2:$A$201)=7)*(YEAR('Daily Expenses'!$A$2:$A$201)=YEAR(TODAY()))*('Daily Expenses'!$C$2:$C$201="Entertainment")) | I32: =SUMPRODUCT(('Daily Expenses'!$G$2:$G$201)*(MONTH('Daily Expenses'!$A$2:$A$201)=8)*(YEAR('Daily Expenses'!$A$2:$A$201)=YEAR(TODAY()))*('Daily Expenses'!$C$2:$C$201="Entertainment")) | J32: =SUMPRODUCT(('Daily Expenses'!$G$2:$G$201)*(MONTH('Daily Expenses'!$A$2:$A$201)=9)*(YEAR('Daily Expenses'!$A$2:$A$201)=YEAR(TODAY()))*('Daily Expenses'!$C$2:$C$201="Entertainment")) | K32: =SUMPRODUCT(('Daily Expenses'!$G$2:$G$201)*(MONTH('Daily Expenses'!$A$2:$A$201)=10)*(YEAR('Daily Expenses'!$A$2:$A$201)=YEAR(TODAY()))*('Daily Expenses'!$C$2:$C$201="Entertainment")) | L32: =SUMPRODUCT(('Daily Expenses'!$G$2:$G$201)*(MONTH('Daily Expenses'!$A$2:$A$201)=11)*(YEAR('Daily Expenses'!$A$2:$A$201)=YEAR(TODAY()))*('Daily Expenses'!$C$2:$C$201="Entertainment")) | M32: =SUMPRODUCT(('Daily Expenses'!$G$2:$G$201)*(MONTH('Daily Expenses'!$A$2:$A$201)=12)*(YEAR('Daily Expenses'!$A$2:$A$201)=YEAR(TODAY()))*('Daily Expenses'!$C$2:$C$201="Entertainment"))
A33: Other | B33: =SUMPRODUCT(('Daily Expenses'!$G$2:$G$201)*(MONTH('Daily Expenses'!$A$2:$A$201)=1)*(YEAR('Daily Expenses'!$A$2:$A$201)=YEAR(TODAY()))*('Daily Expenses'!$C$2:$C$201="Other")) | C33: =SUMPRODUCT(('Daily Expenses'!$G$2:$G$201)*(MONTH('Daily Expenses'!$A$2:$A$201)=2)*(YEAR('Daily Expenses'!$A$2:$A$201)=YEAR(TODAY()))*('Daily Expenses'!$C$2:$C$201="Other")) | D33: =SUMPRODUCT(('Daily Expenses'!$G$2:$G$201)*(MONTH('Daily Expenses'!$A$2:$A$201)=3)*(YEAR('Daily Expenses'!$A$2:$A$201)=YEAR(TODAY()))*('Daily Expenses'!$C$2:$C$201="Other")) | E33: =SUMPRODUCT(('Daily Expenses'!$G$2:$G$201)*(MONTH('Daily Expenses'!$A$2:$A$201)=4)*(YEAR('Daily Expenses'!$A$2:$A$201)=YEAR(TODAY()))*('Daily Expenses'!$C$2:$C$201="Other")) | F33: =SUMPRODUCT(('Daily Expenses'!$G$2:$G$201)*(MONTH('Daily Expenses'!$A$2:$A$201)=5)*(YEAR('Daily Expenses'!$A$2:$A$201)=YEAR(TODAY()))*('Daily Expenses'!$C$2:$C$201="Other")) | G33: =SUMPRODUCT(('Daily Expenses'!$G$2:$G$201)*(MONTH('Daily Expenses'!$A$2:$A$201)=6)*(YEAR('Daily Expenses'!$A$2:$A$201)=YEAR(TODAY()))*('Daily Expenses'!$C$2:$C$201="Other")) | H33: =SUMPRODUCT(('Daily Expenses'!$G$2:$G$201)*(MONTH('Daily Expenses'!$A$2:$A$201)=7)*(YEAR('Daily Expenses'!$A$2:$A$201)=YEAR(TODAY()))*('Daily Expenses'!$C$2:$C$201="Other")) | I33: =SUMPRODUCT(('Daily Expenses'!$G$2:$G$201)*(MONTH('Daily Expenses'!$A$2:$A$201)=8)*(YEAR('Daily Expenses'!$A$2:$A$201)=YEAR(TODAY()))*('Daily Expenses'!$C$2:$C$201="Other")) | J33: =SUMPRODUCT(('Daily Expenses'!$G$2:$G$201)*(MONTH('Daily Expenses'!$A$2:$A$201)=9)*(YEAR('Daily Expenses'!$A$2:$A$201)=YEAR(TODAY()))*('Daily Expenses'!$C$2:$C$201="Other")) | K33: =SUMPRODUCT(('Daily Expenses'!$G$2:$G$201)*(MONTH('Daily Expenses'!$A$2:$A$201)=10)*(YEAR('Daily Expenses'!$A$2:$A$201)=YEAR(TODAY()))*('Daily Expenses'!$C$2:$C$201="Other")) | L33: =SUMPRODUCT(('Daily Expenses'!$G$2:$G$201)*(MONTH('Daily Expenses'!$A$2:$A$201)=11)*(YEAR('Daily Expenses'!$A$2:$A$201)=YEAR(TODAY()))*('Daily Expenses'!$C$2:$C$201="Other")) | M33: =SUMPRODUCT(('Daily Expenses'!$G$2:$G$201)*(MONTH('Daily Expenses'!$A$2:$A$201)=12)*(YEAR('Daily Expenses'!$A$2:$A$201)=YEAR(TODAY()))*('Daily Expenses'!$C$2:$C$201="Other"))

Sheet Category Analysis
A1: Category Analysis
A2: Category | B2: Total Spending | C2: % of Total | D2: Transactions | E2: Avg / Transaction
A3: Food | B3: =SUMIF('Daily Expenses'!$C:$C,"Food",'Daily Expenses'!$G:$G) | C3: =IFERROR(B3/SUM('Daily Expenses'!$G$2:$G$201),0) | D3: =COUNTIF('Daily Expenses'!$C:$C,"Food") | E3: =IFERROR(B3/D3,0)
A4: Vegetables | B4: =SUMIF('Daily Expenses'!$C:$C,"Vegetables",'Daily Expenses'!$G:$G) | C4: =IFERROR(B4/SUM('Daily Expenses'!$G$2:$G$201),0) | D4: =COUNTIF('Daily Expenses'!$C:$C,"Vegetables") | E4: =IFERROR(B4/D4,0)
A5: Meat | B5: =SUMIF('Daily Expenses'!$C:$C,"Meat",'Daily Expenses'!$G:$G) | C5: =IFERROR(B5/SUM('Daily Expenses'!$G$2:$G$201),0) | D5: =COUNTIF('Daily Expenses'!$C:$C,"Meat") | E5: =IFERROR(B5/D5,0)
A6: Fish | B6: =SUMIF('Daily Expenses'!$C:$C,"Fish",'Daily Expenses'!$G:$G) | C6: =IFERROR(B6/SUM('Daily Expenses'!$G$2:$G$201),0) | D6: =COUNTIF('Daily Expenses'!$C:$C,"Fish") | E6: =IFERROR(B6/D6,0)
A7: Protein | B7: =SUMIF('Daily Expenses'!$C:$C,"Protein",'Daily Expenses'!$G:$G) | C7: =IFERROR(B7/SUM('Daily Expenses'!$G$2:$G$201),0) | D7: =COUNTIF('Daily Expenses'!$C:$C,"Protein") | E7: =IFERROR(B7/D7,0)
A8: Snacks | B8: =SUMIF('Daily Expenses'!$C:$C,"Snacks",'Daily Expenses'!$G:$G) | C8: =IFERROR(B8/SUM('Daily Expenses'!$G$2:$G$201),0) | D8: =COUNTIF('Daily Expenses'!$C:$C,"Snacks") | E8: =IFERROR(B8/D8,0)
A9: Drinks | B9: =SUMIF('Daily Expenses'!$C:$C,"Drinks",'Daily Expenses'!$G:$G) | C9: =IFERROR(B9/SUM('Daily Expenses'!$G$2:$G$201),0) | D9: =COUNTIF('Daily Expenses'!$C:$C,"Drinks") | E9: =IFERROR(B9/D9,0)
A10: Transport | B10: =SUMIF('Daily Expenses'!$C:$C,"Transport",'Daily Expenses'!$G:$G) | C10: =IFERROR(B10/SUM('Daily Expenses'!$G$2:$G$201),0) | D10: =COUNTIF('Daily Expenses'!$C:$C,"Transport") | E10: =IFERROR(B10/D10,0)
A11: Health | B11: =SUMIF('Daily Expenses'!$C:$C,"Health",'Daily Expenses'!$G:$G) | C11: =IFERROR(B11/SUM('Daily Expenses'!$G$2:$G$201),0) | D11: =COUNTIF('Daily Expenses'!$C:$C,"Health") | E11: =IFERROR(B11/D11,0)
A12: Supplements | B12: =SUMIF('Daily Expenses'!$C:$C,"Supplements",'Daily Expenses'!$G:$G) | C12: =IFERROR(B12/SUM('Daily Expenses'!$G$2:$G$201),0) | D12: =COUNTIF('Daily Expenses'!$C:$C,"Supplements") | E12: =IFERROR(B12/D12,0)
A13: Household | B13: =SUMIF('Daily Expenses'!$C:$C,"Household",'Daily Expenses'!$G:$G) | C13: =IFERROR(B13/SUM('Daily Expenses'!$G$2:$G$201),0) | D13: =COUNTIF('Daily Expenses'!$C:$C,"Household") | E13: =IFERROR(B13/D13,0)
A14: Electronics | B14: =SUMIF('Daily Expenses'!$C:$C,"Electronics",'Daily Expenses'!$G:$G) | C14: =IFERROR(B14/SUM('Daily Expenses'!$G$2:$G$201),0) | D14: =COUNTIF('Daily Expenses'!$C:$C,"Electronics") | E14: =IFERROR(B14/D14,0)
A15: Clothing | B15: =SUMIF('Daily Expenses'!$C:$C,"Clothing",'Daily Expenses'!$G:$G) | C15: =IFERROR(B15/SUM('Daily Expenses'!$G$2:$G$201),0) | D15: =COUNTIF('Daily Expenses'!$C:$C,"Clothing") | E15: =IFERROR(B15/D15,0)
A16: Entertainment | B16: =SUMIF('Daily Expenses'!$C:$C,"Entertainment",'Daily Expenses'!$G:$G) | C16: =IFERROR(B16/SUM('Daily Expenses'!$G$2:$G$201),0) | D16: =COUNTIF('Daily Expenses'!$C:$C,"Entertainment") | E16: =IFERROR(B16/D16,0)
A17: Other | B17: =SUMIF('Daily Expenses'!$C:$C,"Other",'Daily Expenses'!$G:$G) | C17: =IFERROR(B17/SUM('Daily Expenses'!$G$2:$G$201),0) | D17: =COUNTIF('Daily Expenses'!$C:$C,"Other") | E17: =IFERROR(B17/D17,0)
A18: TOTAL | B18: =SUM('Daily Expenses'!$G$2:$G$201) | C18: =SUM(C3:C17) | D18: =COUNTA('Daily Expenses'!$C$2:$C$201) | E18: =IFERROR(B18/D18,0)

Sheet Budget Tracking
A1: Budget Tracking & Alerts
A3: Budget vs. Actual Spending
A4: Period | B4: Budget (CHF) | C4: Spent (CHF) | D4: Remaining | E4: % Used | G4: Status
A5: Monthly Budget | B5: 3000 | C5: =SUMPRODUCT((MONTH('Daily Expenses'!$A$2:$A$201)=MONTH(TODAY()))*(YEAR('Daily Expenses'!$A$2:$A$201)=YEAR(TODAY()))*'Daily Expenses'!$G$2:$G$201) | D5: =B5-C5 | E5: =IFERROR(C5/B5,0) | G5: =IF(E5>1,"🔴 OVER BUDGET!",IF(E5>0.8,"🟡 WARNING — Near Limit","🟢 On Track"))
A7: Weekly Budget | B7: 700 | C7: =SUMPRODUCT(('Daily Expenses'!$A$2:$A$201>=TODAY()-WEEKDAY(TODAY(),2)+1)*('Daily Expenses'!$A$2:$A$201<=TODAY()-WEEKDAY(TODAY(),2)+7)*'Daily Expenses'!$G$2:$G$201) | D7: =B7-C7 | E7: =IFERROR(C7/B7,0) | G7: =IF(E7>1,"🔴 OVER BUDGET!",IF(E7>0.8,"🟡 WARNING — Near Limit","🟢 On Track"))
A9: Daily Average | B9: 100 | C9: =IFERROR(SUMPRODUCT(('Daily Expenses'!$G$2:$G$201<>"")*'Daily Expenses'!$G$2:$G$201)/SUMPRODUCT(--('Daily Expenses'!$G$2:$G$201<>"")),0) | D9: =B9-C9 | E9: =IFERROR(C9/B9,0) | G9: =IF(E9>1,"🔴 OVER BUDGET!",IF(E9>0.8,"🟡 WARNING — Near Limit","🟢 On Track"))
A12: Budget Tips
A13: • Edit the Budget (CHF) cells in column B to set your personal targets.
A14: • All spending figures update automatically from the Daily Expenses sheet.
A15: • Green = under 80% used | Yellow = 80-100% | Red = over budget

Sheet Charts & Analytics
A1: Charts & Analytics
S2: Store | T2: Total
S3: Migros | T3: =SUMIF('Daily Expenses'!$D:$D,"Migros",'Daily Expenses'!$G:$G)
S4: Coop | T4: =SUMIF('Daily Expenses'!$D:$D,"Coop",'Daily Expenses'!$G:$G)
S5: SBB | T5: =SUMIF('Daily Expenses'!$D:$D,"SBB",'Daily Expenses'!$G:$G)
S6: Apotheke | T6: =SUMIF('Daily Expenses'!$D:$D,"Apotheke",'Daily Expenses'!$G:$G)
S7: Sportxx | T7: =SUMIF('Daily Expenses'!$D:$D,"Sportxx",'Daily Expenses'!$G:$G)
S8: Media Markt | T8: =SUMIF('Daily Expenses'!$D:$D,"Media Markt",'Daily Expenses'!$G:$G)
S9: Netflix | T9: =SUMIF('Daily Expenses'!$D:$D,"Netflix",'Daily Expenses'!$G:$G)
S10: Fitness Park | T10: =SUMIF('Daily Expenses'!$D:$D,"Fitness Park",'Daily Expenses'!$G:$G)
